group_by_continuous_sequence/LICENSE
group_by_continuous_sequence/README.MD
group_by_continuous_sequence/__init__.py
group_by_continuous_sequence/requirements.txt
group_by_continuous_sequence/thirdparty.json
group_by_continuous_sequence-0.10.dist-info/LICENSE.rst
group_by_continuous_sequence-0.10.dist-info/METADATA
group_by_continuous_sequence-0.10.dist-info/WHEEL
group_by_continuous_sequence-0.10.dist-info/top_level.txt
group_by_continuous_sequence-0.10.dist-info/RECORD
