Metadata-Version: 2.1
Name: group-by-continuous-sequence
Version: 0.10
Summary: Groups lists/NumPy arrays by continuous sequence
Home-page: https://github.com/hansalemaos/group_by_continuous_sequence
Author: Johannes Fischer
Author-email: <aulasparticularesdealemaosp@gmail.com>
License: MIT
Keywords: numpy,group,list,sequence
Classifier: Development Status :: 4 - Beta
Classifier: Programming Language :: Python :: 3 :: Only
Classifier: Programming Language :: Python :: 3.9
Classifier: Topic :: Scientific/Engineering :: Visualization
Classifier: Topic :: Software Development :: Libraries :: Python Modules
Classifier: Topic :: Text Editors :: Text Processing
Classifier: Topic :: Text Processing :: General
Classifier: Topic :: Text Processing :: Indexing
Classifier: Topic :: Text Processing :: Filters
Classifier: Topic :: Utilities
License-File: LICENSE.rst
Requires-Dist: flatten-everything
Requires-Dist: intersection-grouper
Requires-Dist: numpy
Requires-Dist: pandas
